gspy/__init__.py
gspy/_version.py
gspy/file_handlers/__init__.py
gspy/file_handlers/aseg_gdf_handler.py
gspy/file_handlers/csv_handler.py
gspy/file_handlers/file_handler_abc.py
gspy/file_handlers/loupe_handler.py
gspy/file_handlers/workbench_handler.py
gspy/file_handlers/xyz_handler.py
gspy/gs_dataarray/Coordinate.py
gspy/gs_dataarray/DataArray.py
gspy/gs_dataarray/Spatial_ref.py
gspy/gs_dataarray/__init__.py
gspy/gs_dataset/Dataset.py
gspy/gs_dataset/Raster.py
gspy/gs_dataset/System.py
gspy/gs_dataset/Tabular.py
gspy/gs_dataset/__init__.py
gspy/gs_datatree/Container.py
gspy/gs_datatree/Survey.py
gspy/gs_datatree/__init__.py
gspy/metadata/Metadata.py
gspy/metadata/Variable_metadata.py
gspy/metadata/__init__.py
gspy/utilities/CRS.py
gspy/utilities/__init__.py
gspy/utilities/maths.py
gspy/examples/README.rst
gspy/examples/Creating_GS_Files/README.rst
gspy/examples/Creating_GS_Files/Resolve_metadata_template.yml
gspy/examples/Creating_GS_Files/help_I_have_no_variable_metadata.py
gspy/examples/Creating_GS_Files/plot_aseg_tempest.py
gspy/examples/Creating_GS_Files/plot_csv_loupe.py
gspy/examples/Creating_GS_Files/plot_csv_magnetics.py
gspy/examples/Creating_GS_Files/plot_csv_resolve.py
gspy/examples/Creating_GS_Files/plot_csv_skytem.py
gspy/examples/Creating_GS_Files/plot_loupe_csv.py
gspy/examples/Creating_GS_Files/plot_magnetics_csv.py
gspy/examples/Creating_GS_Files/plot_resolve_csv.py
gspy/examples/Creating_GS_Files/plot_skytem_csv.py
gspy/examples/Creating_GS_Files/plot_tempest_aseg.py
gspy/examples/Creating_GS_Files/plot_tifs.py
gspy/examples/Creating_GS_Files/plot_xyz_workbench_to_netcdf.py
gspy/examples/Creating_GS_Files/template_md_loupe.yml
gspy/examples/Creating_GS_Files/template_md_resolve.yml
gspy/examples/Creating_GS_Files/template_md_resolve_empty.yml
gspy/examples/Creating_GS_Files/template_md_skytem.yml
gspy/examples/Creating_GS_Files/template_md_survey.yml
gspy/examples/Creating_GS_Files/template_survey_empty.yml
gspy-2.2.5.dist-info/METADATA
gspy-2.2.5.dist-info/WHEEL
gspy-2.2.5.dist-info/licenses/LICENSE.md
gspy-2.2.5.dist-info/RECORD
