Metadata-Version: 2.4
Name: gspy
Version: 2.2.5
Summary: gspy converts commonly used data formats into a netcdf file honoring our GS convention.
Project-URL: Documentation, https://usgs.github.io/gspy/
Project-URL: Issues, https://https://github.com/usgs/gspy/issues
Project-URL: Source, https://https://github.com/usgs/gspy
Project-URL: Homepage, https://usgs.github.io/gspy/
Project-URL: source_archive, https://usgs.github.io/gspy/archive/7f117bca867006c40e09ac9acbdd5a776661f0a8.zip
Author-email: Leon Foks <nfoks@contractor.usgs.gov>, Stephanie James <sjames@usgs.gov>, Burke Minsley <bminsley@usgs.gov>
License-File: LICENSE.md
Keywords: netcdf,xarray
Classifier: License :: OSI Approved
Classifier: License :: OSI Approved :: MIT License
Classifier: Programming Language :: Python :: 3
Classifier: Topic :: Scientific/Engineering
Requires-Python: >=3.10
Requires-Dist: chardet
Requires-Dist: fortranformat
Requires-Dist: h5netcdf
Requires-Dist: h5py
Requires-Dist: matplotlib
Requires-Dist: netcdf4
Requires-Dist: numpy
Requires-Dist: pandas
Requires-Dist: pygmt
Requires-Dist: pyproj
Requires-Dist: pyyaml
Requires-Dist: rioxarray
Requires-Dist: scipy
Requires-Dist: xarray
